data_patterns/__init__.py
data_patterns/constants.py
data_patterns/data_patterns.py
data_patterns/encodings.py
data_patterns/parser.py
data_patterns/transform.py
data_patterns-0.1.24.dist-info/AUTHORS.rst
data_patterns-0.1.24.dist-info/LICENSE
data_patterns-0.1.24.dist-info/METADATA
data_patterns-0.1.24.dist-info/WHEEL
data_patterns-0.1.24.dist-info/top_level.txt
data_patterns-0.1.24.dist-info/RECORD
