Metadata-Version: 2.1
Name: data-patterns
Version: 0.1.24
Summary: Package for generating and evaluating patterns in quantitative reports
Home-page: https://github.com/DeNederlandscheBank/data-patterns
Author: De Nederlandsche Bank
Author-email: ECDB_berichten@dnb.nl
License: MIT/X license
Keywords: data_patterns
Platform: UNKNOWN
Classifier: Development Status :: 2 - Pre-Alpha
Classifier: Intended Audience :: Financial and Insurance Industry
Classifier: Intended Audience :: Developers
Classifier: Intended Audience :: Education
Classifier: License :: OSI Approved :: MIT License
Classifier: Natural Language :: English
Classifier: Programming Language :: Python :: 3.6
Classifier: Programming Language :: Python :: 3.7
Classifier: Programming Language :: Python :: 3.8
Requires-Python: >=3.0, !=3.0.*, !=3.1.*, !=3.2.*, !=3.3.*, !=3.4.*
Requires-Dist: pandas
Requires-Dist: numpy
Requires-Dist: xlsxwriter
Requires-Dist: tqdm
